km3modules/__init__.py
km3modules/ahrs.py
km3modules/common.py
km3modules/communication.py
km3modules/dummy.py
km3modules/fit.py
km3modules/hardware.py
km3modules/hits.py
km3modules/io.py
km3modules/k40.py
km3modules/mc.py
km3modules/parser.py
km3modules/plot.py
km3modules/topology.py
km3modules/tests/__init__.py
km3modules/tests/test_common.py
km3modules/tests/test_foo.py
km3modules/tests/test_hits.py
km3modules/tests/test_io.py
km3modules/tests/test_mc.py
km3pipe/__init__.py
km3pipe/__version__.py
km3pipe/calib.py
km3pipe/cmd.py
km3pipe/constants.py
km3pipe/controlhost.py
km3pipe/dataclass_templates.py
km3pipe/dataclasses.py
km3pipe/extras.py
km3pipe/hardware.py
km3pipe/logger.py
km3pipe/math.py
km3pipe/mc.py
km3pipe/physics.py
km3pipe/plot.py
km3pipe/pyproject.toml
km3pipe/shell.py
km3pipe/sys.py
km3pipe/testing.py
km3pipe/time.py
km3pipe/tools.py
km3pipe/version.py
km3pipe/io/__init__.py
km3pipe/io/ch.py
km3pipe/io/clb.py
km3pipe/io/daq.py
km3pipe/io/evt.py
km3pipe/io/hdf5.py
km3pipe/io/i3.py
km3pipe/io/offline.py
km3pipe/io/tests/__init__.py
km3pipe/io/tests/test_ch.py
km3pipe/io/tests/test_clb.py
km3pipe/io/tests/test_daq.py
km3pipe/io/tests/test_evt.py
km3pipe/io/tests/test_hdf5.py
km3pipe/io/tests/test_offline.py
km3pipe/style/__init__.py
km3pipe/style/alba.py
km3pipe/style/default.py
km3pipe/style/johannes.py
km3pipe/style/jonas_phd.py
km3pipe/style/km3pipe.py
km3pipe/style/km3pipe_notebook.py
km3pipe/style/km3pipe_poster.py
km3pipe/style/km3pipe_talk.py
km3pipe/style/moritz.py
km3pipe/stylelib/alba.mplstyle
km3pipe/stylelib/johannes.mplstyle
km3pipe/stylelib/jonas-phd.mplstyle
km3pipe/stylelib/jvs.mplstyle
km3pipe/stylelib/km3pipe-notebook.mplstyle
km3pipe/stylelib/km3pipe-poster.mplstyle
km3pipe/stylelib/km3pipe-talk.mplstyle
km3pipe/stylelib/km3pipe.mplstyle
km3pipe/stylelib/moritz.mplstyle
km3pipe/stylelib/serifs.mplstyle
km3pipe/tests/__init__.py
km3pipe/tests/test_calib.py
km3pipe/tests/test_cmd.py
km3pipe/tests/test_controlhost.py
km3pipe-10.0.3.dist-info/LICENSE
km3pipe-10.0.3.dist-info/METADATA
km3pipe-10.0.3.dist-info/WHEEL
km3pipe-10.0.3.dist-info/entry_points.txt
km3pipe-10.0.3.dist-info/top_level.txt
km3pipe-10.0.3.dist-info/RECORD
