Metadata-Version: 2.1
Name: km3pipe
Version: 10.0.3
Summary: "An analysis framework for KM3NeT"
Home-page: https://git.km3net.de/km3py/km3pipe
Author: Tamas Gal and Moritz Lotze
Author-email: tgal@km3net.de
Maintainer: Tamas Gal
Maintainer-email: tgal@km3net.de
License: MIT
Keywords: neutrino,astroparticle,physics,HEP,pipeline
Classifier: Development Status :: 5 - Production/Stable
Classifier: Intended Audience :: Developers
Classifier: Intended Audience :: Science/Research
Classifier: License :: OSI Approved :: BSD License
Classifier: Operating System :: OS Independent
Classifier: Programming Language :: Python
Classifier: Programming Language :: Python :: 3
Classifier: Programming Language :: Python :: 3 :: Only
Classifier: Programming Language :: Python :: 3.10
Classifier: Programming Language :: Python :: 3.11
Classifier: Programming Language :: Python :: 3.12
Classifier: Topic :: Scientific/Engineering
Requires-Python: >=3.10
License-File: LICENSE
Requires-Dist: awkward >=2
Requires-Dist: docopt
Requires-Dist: h5py
Requires-Dist: km3db >=0.6.0
Requires-Dist: km3io >=1.2.2
Requires-Dist: matplotlib >=3.0.0
Requires-Dist: numba >=0.49.0
Requires-Dist: numpy >=2
Requires-Dist: packaging >=22.0
Requires-Dist: particle >=0.8.0
Requires-Dist: passlib
Requires-Dist: requests
Requires-Dist: setuptools >=40.6.2
Requires-Dist: setuptools-scm
Requires-Dist: tables >=3.10
Requires-Dist: thepipe >=1.3.7
Requires-Dist: toml
Requires-Dist: tqdm
Provides-Extra: all
Requires-Dist: ipykernel ; extra == 'all'
Requires-Dist: pandas ; extra == 'all'
Requires-Dist: pypandoc ; extra == 'all'
Requires-Dist: scipy >=1.3.1 ; extra == 'all'
Requires-Dist: seaborn ; extra == 'all'
Requires-Dist: km3astro ; extra == 'all'
Requires-Dist: km3flux ; extra == 'all'
Requires-Dist: urwid ; extra == 'all'
Provides-Extra: dev
Requires-Dist: ipykernel ; extra == 'dev'
Requires-Dist: pandas ; extra == 'dev'
Requires-Dist: pypandoc ; extra == 'dev'
Requires-Dist: scipy >=1.3.1 ; extra == 'dev'
Requires-Dist: seaborn ; extra == 'dev'
Requires-Dist: km3astro ; extra == 'dev'
Requires-Dist: km3flux ; extra == 'dev'
Requires-Dist: urwid ; extra == 'dev'
Requires-Dist: black ==22.3.0 ; extra == 'dev'
Requires-Dist: km3net-testdata >=0.4.0 ; extra == 'dev'
Requires-Dist: mock ; extra == 'dev'
Requires-Dist: numpydoc ; extra == 'dev'
Requires-Dist: pillow ; extra == 'dev'
Requires-Dist: pydocstyle ; extra == 'dev'
Requires-Dist: pytest ; extra == 'dev'
Requires-Dist: pytest-cov ; extra == 'dev'
Requires-Dist: pytest-flake8 ; extra == 'dev'
Requires-Dist: pylint ; extra == 'dev'
Requires-Dist: pytest-watch ; extra == 'dev'
Requires-Dist: sphinx-gallery ; extra == 'dev'
Requires-Dist: sphinx-rtd-theme >=0.3 ; extra == 'dev'
Requires-Dist: sphinx >=5.2.1 ; extra == 'dev'
Requires-Dist: sphinxcontrib-napoleon >=0.6.1 ; extra == 'dev'
Requires-Dist: sphinxcontrib-programoutput >=0.11 ; extra == 'dev'
Requires-Dist: sphinxcontrib-websupport >=1.0.1 ; extra == 'dev'
Requires-Dist: sphinx-autoapi ; extra == 'dev'
Requires-Dist: twine ; extra == 'dev'
Requires-Dist: wheel ; extra == 'dev'
